LICENSE.txt
MANIFEST.in
README.rst
requirements.txt
setup.py
bgpack/__init__.py
bgpack/cli.py
bgpack/globals.py
bgpack/main.py
bgpack/utils.py
bgpack.egg-info/PKG-INFO
bgpack.egg-info/SOURCES.txt
bgpack.egg-info/dependency_links.txt
bgpack.egg-info/entry_points.txt
bgpack.egg-info/requires.txt
bgpack.egg-info/top_level.txt
bgpack/implementation/__init__.py
bgpack/implementation/implementation.py
bgpack/implementation/parser.py
bgpack/implementation/bitarray01/__init__.py
bgpack/implementation/bitarray01/mapper.py
bgpack/implementation/bitarray01/packer.py
bgpack/implementation/bitarray01/unpacker.py
bgpack/implementation/bytearray/__init__.py
bgpack/implementation/bytearray/mapper.py
bgpack/implementation/bytearray/packer.py
bgpack/implementation/bytearray/unpacker.py
bgpack/map/__init__.py
bgpack/map/mapper.py
bgpack/map/utils.py
bgpack/pack/__init__.py
bgpack/pack/pack.py
bgpack/pack/utils.py
bgpack/parse/__init__.py
bgpack/parse/cadd.py
bgpack/parse/csv.py
bgpack/parse/tabix.py
bgpack/parse/utils.py
bgpack/tree/__init__.py
bgpack/tree/cli.py
bgpack/tree/main.py
bgpack/tree/parser.py
bgpack/tree/unpacker.py
bgpack/unpack/__init__.py
bgpack/unpack/file.py
bgpack/unpack/files.py
test/test_int2bits.py
test/test_multiparsers.py
test/test_value.py
test/test_values.py