Metadata-Version: 1.0
Name: bgpack
Version: 0.8
Summary: BBGLab tool
Home-page: UNKNOWN
Author: Barcelona Biomedical Genomics Lab
Author-email: bbglab@irbbarcelona.org
License: Apache Software License 2.0
Platform: UNKNOWN
